{".class":"MypyFile","_fullname":"trio._highlevel_ssl_helpers","future_import_flags":["annotations"],"is_partial_stub_package":false,"is_stub":false,"names":{".class":"SymbolTable","Awaitable":{".class":"SymbolTableNode","cross_ref":"typing.Awaitable","kind":"Gdef"},"Callable":{".class":"SymbolTableNode","cross_ref":"typing.Callable","kind":"Gdef"},"DEFAULT_DELAY":{".class":"SymbolTableNode","cross_ref":"trio._highlevel_open_tcp_stream.DEFAULT_DELAY","kind":"Gdef"},"NoReturn":{".class":"SymbolTableNode","cross_ref":"typing.NoReturn","kind":"Gdef"},"SocketStream":{".class":"SymbolTableNode","cross_ref":"trio._highlevel_socket.SocketStream","kind":"Gdef"},"T":{".class":"SymbolTableNode","kind":"Gdef","node":{".class":"TypeVarExpr","default":{".class":"AnyType","missing_import_name":null,"source_any":null,"type_of_any":4},"fullname":"trio._highlevel_ssl_helpers.T","name":"T","upper_bound":"builtins.object","values":[],"variance":0}},"TYPE_CHECKING":{".class":"SymbolTableNode","cross_ref":"typing.TYPE_CHECKING","kind":"Gdef"},"TypeVar":{".class":"SymbolTableNode","cross_ref":"typing.TypeVar","kind":"Gdef"},"__annotations__":{".class":"SymbolTableNode","kind":"Gdef","node":{".class":"Var","flags":["is_ready"],"fullname":"trio._highlevel_ssl_helpers.__annotations__","name":"__annotations__","type":{".class":"Instance","args":["builtins.str",{".class":"AnyType","missing_import_name":null,"source_any":null,"type_of_any":6}],"extra_attrs":null,"type_ref":"builtins.dict"}}},"__doc__":{".class":"SymbolTableNode","kind":"Gdef","node":{".class":"Var","flags":["is_ready"],"fullname":"trio._highlevel_ssl_helpers.__doc__","name":"__doc__","type":"builtins.str"}},"__file__":{".class":"SymbolTableNode","kind":"Gdef","node":{".class":"Var","flags":["is_ready"],"fullname":"trio._highlevel_ssl_helpers.__file__","name":"__file__","type":"builtins.str"}},"__name__":{".class":"SymbolTableNode","kind":"Gdef","node":{".class":"Var","flags":["is_ready"],"fullname":"trio._highlevel_ssl_helpers.__name__","name":"__name__","type":"builtins.str"}},"__package__":{".class":"SymbolTableNode","kind":"Gdef","node":{".class":"Var","flags":["is_ready"],"fullname":"trio._highlevel_ssl_helpers.__package__","name":"__package__","type":"builtins.str"}},"__spec__":{".class":"SymbolTableNode","kind":"Gdef","node":{".class":"Var","flags":["is_ready"],"fullname":"trio._highlevel_ssl_helpers.__spec__","name":"__spec__","type":"_frozen_importlib.ModuleSpec"}},"annotations":{".class":"SymbolTableNode","cross_ref":"__future__.annotations","kind":"Gdef"},"open_ssl_over_tcp_listeners":{".class":"SymbolTableNode","kind":"Gdef","node":{".class":"FuncDef","abstract_status":0,"arg_kinds":[0,0,5,5,5],"arg_names":["port","ssl_context","host","https_compatible","backlog"],"dataclass_transform_spec":null,"deprecated":null,"flags":["is_coroutine"],"fullname":"trio._highlevel_ssl_helpers.open_ssl_over_tcp_listeners","name":"open_ssl_over_tcp_listeners","type":{".class":"CallableType","arg_kinds":[0,0,5,5,5],"arg_names":["port","ssl_context","host","https_compatible","backlog"],"arg_types":["builtins.int","ssl.SSLContext",{".class":"UnionType","items":["builtins.str","builtins.bytes",{".class":"NoneType"}],"uses_pep604_syntax":true},"builtins.bool",{".class":"UnionType","items":["builtins.int",{".class":"NoneType"}],"uses_pep604_syntax":true}],"bound_args":[],"def_extras":{"first_arg":null},"fallback":"builtins.function","from_concatenate":false,"implicit":false,"imprecise_arg_kinds":false,"is_ellipsis_args":false,"name":"open_ssl_over_tcp_listeners","ret_type":{".class":"Instance","args":[{".class":"AnyType","missing_import_name":null,"source_any":null,"type_of_any":6},{".class":"AnyType","missing_import_name":null,"source_any":null,"type_of_any":6},{".class":"Instance","args":[{".class":"Instance","args":["trio._highlevel_socket.SocketStream"],"extra_attrs":null,"type_ref":"trio._ssl.SSLListener"}],"extra_attrs":null,"type_ref":"builtins.list"}],"extra_attrs":null,"type_ref":"typing.Coroutine"},"type_guard":null,"type_is":null,"unpack_kwargs":false,"variables":[]}}},"open_ssl_over_tcp_stream":{".class":"SymbolTableNode","kind":"Gdef","node":{".class":"FuncDef","abstract_status":0,"arg_kinds":[0,0,5,5,5],"arg_names":["host","port","https_compatible","ssl_context","happy_eyeballs_delay"],"dataclass_transform_spec":null,"deprecated":null,"flags":["is_coroutine"],"fullname":"trio._highlevel_ssl_helpers.open_ssl_over_tcp_stream","name":"open_ssl_over_tcp_stream","type":{".class":"CallableType","arg_kinds":[0,0,5,5,5],"arg_names":["host","port","https_compatible","ssl_context","happy_eyeballs_delay"],"arg_types":[{".class":"UnionType","items":["builtins.str","builtins.bytes"],"uses_pep604_syntax":true},"builtins.int","builtins.bool",{".class":"UnionType","items":["ssl.SSLContext",{".class":"NoneType"}],"uses_pep604_syntax":true},{".class":"UnionType","items":["builtins.float",{".class":"NoneType"}],"uses_pep604_syntax":true}],"bound_args":[],"def_extras":{"first_arg":null},"fallback":"builtins.function","from_concatenate":false,"implicit":false,"imprecise_arg_kinds":false,"is_ellipsis_args":false,"name":"open_ssl_over_tcp_stream","ret_type":{".class":"Instance","args":[{".class":"AnyType","missing_import_name":null,"source_any":null,"type_of_any":6},{".class":"AnyType","missing_import_name":null,"source_any":null,"type_of_any":6},{".class":"Instance","args":["trio._highlevel_socket.SocketStream"],"extra_attrs":null,"type_ref":"trio._ssl.SSLStream"}],"extra_attrs":null,"type_ref":"typing.Coroutine"},"type_guard":null,"type_is":null,"unpack_kwargs":false,"variables":[]}}},"serve_ssl_over_tcp":{".class":"SymbolTableNode","kind":"Gdef","node":{".class":"FuncDef","abstract_status":0,"arg_kinds":[0,0,0,5,5,5,5,5],"arg_names":["handler","port","ssl_context","host","https_compatible","backlog","handler_nursery","task_status"],"dataclass_transform_spec":null,"deprecated":null,"flags":["is_coroutine"],"fullname":"trio._highlevel_ssl_helpers.serve_ssl_over_tcp","name":"serve_ssl_over_tcp","type":{".class":"CallableType","arg_kinds":[0,0,0,5,5,5,5,5],"arg_names":["handler","port","ssl_context","host","https_compatible","backlog","handler_nursery","task_status"],"arg_types":[{".class":"CallableType","arg_kinds":[0],"arg_names":[null],"arg_types":[{".class":"Instance","args":["trio._highlevel_socket.SocketStream"],"extra_attrs":null,"type_ref":"trio._ssl.SSLStream"}],"bound_args":[],"def_extras":{},"fallback":"builtins.function","from_concatenate":false,"implicit":false,"imprecise_arg_kinds":false,"is_ellipsis_args":false,"name":null,"ret_type":{".class":"Instance","args":["builtins.object"],"extra_attrs":null,"type_ref":"typing.Awaitable"},"type_guard":null,"type_is":null,"unpack_kwargs":false,"variables":[]},"builtins.int","ssl.SSLContext",{".class":"UnionType","items":["builtins.str","builtins.bytes",{".class":"NoneType"}],"uses_pep604_syntax":true},"builtins.bool",{".class":"UnionType","items":["builtins.int",{".class":"NoneType"}],"uses_pep604_syntax":true},{".class":"UnionType","items":["trio._core._run.Nursery",{".class":"NoneType"}],"uses_pep604_syntax":true},{".class":"Instance","args":[{".class":"Instance","args":[{".class":"Instance","args":["trio._highlevel_socket.SocketStream"],"extra_attrs":null,"type_ref":"trio._ssl.SSLListener"}],"extra_attrs":null,"type_ref":"builtins.list"}],"extra_attrs":null,"type_ref":"trio._core._run.TaskStatus"}],"bound_args":[],"def_extras":{"first_arg":null},"fallback":"builtins.function","from_concatenate":false,"implicit":false,"imprecise_arg_kinds":false,"is_ellipsis_args":false,"name":"serve_ssl_over_tcp","ret_type":{".class":"Instance","args":[{".class":"AnyType","missing_import_name":null,"source_any":null,"type_of_any":6},{".class":"AnyType","missing_import_name":null,"source_any":null,"type_of_any":6},{".class":"UninhabitedType"}],"extra_attrs":null,"type_ref":"typing.Coroutine"},"type_guard":null,"type_is":null,"unpack_kwargs":false,"variables":[]}}},"ssl":{".class":"SymbolTableNode","cross_ref":"ssl","kind":"Gdef"},"trio":{".class":"SymbolTableNode","cross_ref":"trio","kind":"Gdef"}},"path":"/Library/Frameworks/Python.framework/Versions/3.13/lib/python3.13/site-packages/trio/_highlevel_ssl_helpers.py"}