{".class":"MypyFile","_fullname":"trio._core._ki","future_import_flags":["annotations"],"is_partial_stub_package":false,"is_stub":false,"names":{".class":"SymbolTable","Callable":{".class":"SymbolTableNode","cross_ref":"typing.Callable","kind":"Gdef"},"GLOBAL_RUN_CONTEXT":{".class":"SymbolTableNode","cross_ref":"trio._core._run_context.GLOBAL_RUN_CONTEXT","kind":"Gdef"},"Generic":{".class":"SymbolTableNode","cross_ref":"typing.Generic","kind":"Gdef"},"KIManager":{".class":"SymbolTableNode","kind":"Gdef","node":{".class":"TypeInfo","_promote":[],"abstract_attributes":[],"alt_promote":null,"bases":["builtins.object"],"dataclass_transform_spec":null,"declared_metaclass":null,"defn":{".class":"ClassDef","fullname":"trio._core._ki.KIManager","name":"KIManager","type_vars":[]},"deletable_attributes":[],"deprecated":null,"flags":[],"fullname":"trio._core._ki.KIManager","has_param_spec_type":false,"metaclass_type":null,"metadata":{"attrs":{"attributes":[{"alias":null,"context_column":4,"context_line":242,"converter_init_type":null,"has_converter":false,"has_default":true,"init":true,"init_type":{".class":"UnionType","items":[{".class":"CallableType","arg_kinds":[0,0],"arg_names":[null,null],"arg_types":["builtins.int",{".class":"UnionType","items":["types.FrameType",{".class":"NoneType"}],"uses_pep604_syntax":true}],"bound_args":[],"def_extras":{},"fallback":"builtins.function","from_concatenate":false,"implicit":false,"imprecise_arg_kinds":false,"is_ellipsis_args":false,"name":null,"ret_type":{".class":"NoneType"},"type_guard":null,"type_is":null,"unpack_kwargs":false,"variables":[]},{".class":"NoneType"}],"uses_pep604_syntax":true},"kw_only":false,"name":"handler"}],"frozen":false},"attrs_tag":{}},"module_name":"trio._core._ki","mro":["trio._core._ki.KIManager","builtins.object"],"names":{".class":"SymbolTable","_AT":{".class":"SymbolTableNode","kind":"Mdef","node":{".class":"TypeVarExpr","default":{".class":"AnyType","missing_import_name":null,"source_any":null,"type_of_any":4},"fullname":"trio._core._ki.KIManager._AT","name":"_AT","upper_bound":"builtins.object","values":[],"variance":0}},"__attrs_attrs__":{".class":"SymbolTableNode","kind":"Mdef","node":{".class":"Var","flags":["is_classvar","is_ready","allow_incompatible_override"],"fullname":"trio._core._ki.KIManager.__attrs_attrs__","name":"__attrs_attrs__","type":{".class":"TupleType","implicit":false,"items":[{".class":"Instance","args":[{".class":"UnionType","items":[{".class":"CallableType","arg_kinds":[0,0],"arg_names":[null,null],"arg_types":["builtins.int",{".class":"UnionType","items":["types.FrameType",{".class":"NoneType"}],"uses_pep604_syntax":true}],"bound_args":[],"def_extras":{},"fallback":"builtins.function","from_concatenate":false,"implicit":false,"imprecise_arg_kinds":false,"is_ellipsis_args":false,"name":null,"ret_type":{".class":"NoneType"},"type_guard":null,"type_is":null,"unpack_kwargs":false,"variables":[]},{".class":"NoneType"}],"uses_pep604_syntax":true}],"extra_attrs":null,"type_ref":"attr.Attribute"}],"partial_fallback":"trio._core._ki.KIManager.__trio__core__ki_KIManager_AttrsAttributes__"}},"plugin_generated":true},"__ge__":{".class":"SymbolTableNode","kind":"Mdef","node":{".class":"FuncDef","abstract_status":0,"arg_kinds":[0,0],"arg_names":["self","other"],"dataclass_transform_spec":null,"deprecated":null,"flags":[],"fullname":"trio._core._ki.KIManager.__ge__","name":"__ge__","type":{".class":"CallableType","arg_kinds":[0,0],"arg_names":["self","other"],"arg_types":[{".class":"TypeVarType","default":{".class":"AnyType","missing_import_name":null,"source_any":null,"type_of_any":4},"fullname":"trio._core._ki.KIManager._AT","id":-1,"name":"_AT","namespace":"trio._core._ki.KIManager.__ge__","upper_bound":"builtins.object","values":[],"variance":0},{".class":"TypeVarType","default":{".class":"AnyType","missing_import_name":null,"source_any":null,"type_of_any":4},"fullname":"trio._core._ki.KIManager._AT","id":-1,"name":"_AT","namespace":"trio._core._ki.KIManager.__ge__","upper_bound":"builtins.object","values":[],"variance":0}],"bound_args":[],"def_extras":{},"fallback":"builtins.function","from_concatenate":false,"implicit":false,"imprecise_arg_kinds":false,"is_ellipsis_args":false,"name":"__ge__ of KIManager","ret_type":"builtins.bool","type_guard":null,"type_is":null,"unpack_kwargs":false,"variables":[{".class":"TypeVarType","default":{".class":"AnyType","missing_import_name":null,"source_any":null,"type_of_any":4},"fullname":"trio._core._ki.KIManager._AT","id":-1,"name":"_AT","namespace":"trio._core._ki.KIManager.__ge__","upper_bound":"builtins.object","values":[],"variance":0}]}},"plugin_generated":true},"__gt__":{".class":"SymbolTableNode","kind":"Mdef","node":{".class":"FuncDef","abstract_status":0,"arg_kinds":[0,0],"arg_names":["self","other"],"dataclass_transform_spec":null,"deprecated":null,"flags":[],"fullname":"trio._core._ki.KIManager.__gt__","name":"__gt__","type":{".class":"CallableType","arg_kinds":[0,0],"arg_names":["self","other"],"arg_types":[{".class":"TypeVarType","default":{".class":"AnyType","missing_import_name":null,"source_any":null,"type_of_any":4},"fullname":"trio._core._ki.KIManager._AT","id":-1,"name":"_AT","namespace":"trio._core._ki.KIManager.__gt__","upper_bound":"builtins.object","values":[],"variance":0},{".class":"TypeVarType","default":{".class":"AnyType","missing_import_name":null,"source_any":null,"type_of_any":4},"fullname":"trio._core._ki.KIManager._AT","id":-1,"name":"_AT","namespace":"trio._core._ki.KIManager.__gt__","upper_bound":"builtins.object","values":[],"variance":0}],"bound_args":[],"def_extras":{},"fallback":"builtins.function","from_concatenate":false,"implicit":false,"imprecise_arg_kinds":false,"is_ellipsis_args":false,"name":"__gt__ of KIManager","ret_type":"builtins.bool","type_guard":null,"type_is":null,"unpack_kwargs":false,"variables":[{".class":"TypeVarType","default":{".class":"AnyType","missing_import_name":null,"source_any":null,"type_of_any":4},"fullname":"trio._core._ki.KIManager._AT","id":-1,"name":"_AT","namespace":"trio._core._ki.KIManager.__gt__","upper_bound":"builtins.object","values":[],"variance":0}]}},"plugin_generated":true},"__hash__":{".class":"SymbolTableNode","kind":"Mdef","node":{".class":"Var","flags":["is_classvar","is_ready"],"fullname":"trio._core._ki.KIManager.__hash__","name":"__hash__","type":{".class":"NoneType"}},"plugin_generated":true},"__init__":{".class":"SymbolTableNode","kind":"Mdef","node":{".class":"FuncDef","abstract_status":0,"arg_kinds":[0,1],"arg_names":["self","handler"],"dataclass_transform_spec":null,"deprecated":null,"flags":[],"fullname":"trio._core._ki.KIManager.__init__","name":"__init__","type":{".class":"CallableType","arg_kinds":[0,1],"arg_names":["self","handler"],"arg_types":["trio._core._ki.KIManager",{".class":"UnionType","items":[{".class":"CallableType","arg_kinds":[0,0],"arg_names":[null,null],"arg_types":["builtins.int",{".class":"UnionType","items":["types.FrameType",{".class":"NoneType"}],"uses_pep604_syntax":true}],"bound_args":[],"def_extras":{},"fallback":"builtins.function","from_concatenate":false,"implicit":false,"imprecise_arg_kinds":false,"is_ellipsis_args":false,"name":null,"ret_type":{".class":"NoneType"},"type_guard":null,"type_is":null,"unpack_kwargs":false,"variables":[]},{".class":"NoneType"}],"uses_pep604_syntax":true}],"bound_args":[],"def_extras":{},"fallback":"builtins.function","from_concatenate":false,"implicit":false,"imprecise_arg_kinds":false,"is_ellipsis_args":false,"name":"__init__ of KIManager","ret_type":{".class":"NoneType"},"type_guard":null,"type_is":null,"unpack_kwargs":false,"variables":[]}},"plugin_generated":true},"__le__":{".class":"SymbolTableNode","kind":"Mdef","node":{".class":"FuncDef","abstract_status":0,"arg_kinds":[0,0],"arg_names":["self","other"],"dataclass_transform_spec":null,"deprecated":null,"flags":[],"fullname":"trio._core._ki.KIManager.__le__","name":"__le__","type":{".class":"CallableType","arg_kinds":[0,0],"arg_names":["self","other"],"arg_types":[{".class":"TypeVarType","default":{".class":"AnyType","missing_import_name":null,"source_any":null,"type_of_any":4},"fullname":"trio._core._ki.KIManager._AT","id":-1,"name":"_AT","namespace":"trio._core._ki.KIManager.__le__","upper_bound":"builtins.object","values":[],"variance":0},{".class":"TypeVarType","default":{".class":"AnyType","missing_import_name":null,"source_any":null,"type_of_any":4},"fullname":"trio._core._ki.KIManager._AT","id":-1,"name":"_AT","namespace":"trio._core._ki.KIManager.__le__","upper_bound":"builtins.object","values":[],"variance":0}],"bound_args":[],"def_extras":{},"fallback":"builtins.function","from_concatenate":false,"implicit":false,"imprecise_arg_kinds":false,"is_ellipsis_args":false,"name":"__le__ of KIManager","ret_type":"builtins.bool","type_guard":null,"type_is":null,"unpack_kwargs":false,"variables":[{".class":"TypeVarType","default":{".class":"AnyType","missing_import_name":null,"source_any":null,"type_of_any":4},"fullname":"trio._core._ki.KIManager._AT","id":-1,"name":"_AT","namespace":"trio._core._ki.KIManager.__le__","upper_bound":"builtins.object","values":[],"variance":0}]}},"plugin_generated":true},"__lt__":{".class":"SymbolTableNode","kind":"Mdef","node":{".class":"FuncDef","abstract_status":0,"arg_kinds":[0,0],"arg_names":["self","other"],"dataclass_transform_spec":null,"deprecated":null,"flags":[],"fullname":"trio._core._ki.KIManager.__lt__","name":"__lt__","type":{".class":"CallableType","arg_kinds":[0,0],"arg_names":["self","other"],"arg_types":[{".class":"TypeVarType","default":{".class":"AnyType","missing_import_name":null,"source_any":null,"type_of_any":4},"fullname":"trio._core._ki.KIManager._AT","id":-1,"name":"_AT","namespace":"trio._core._ki.KIManager.__lt__","upper_bound":"builtins.object","values":[],"variance":0},{".class":"TypeVarType","default":{".class":"AnyType","missing_import_name":null,"source_any":null,"type_of_any":4},"fullname":"trio._core._ki.KIManager._AT","id":-1,"name":"_AT","namespace":"trio._core._ki.KIManager.__lt__","upper_bound":"builtins.object","values":[],"variance":0}],"bound_args":[],"def_extras":{},"fallback":"builtins.function","from_concatenate":false,"implicit":false,"imprecise_arg_kinds":false,"is_ellipsis_args":false,"name":"__lt__ of KIManager","ret_type":"builtins.bool","type_guard":null,"type_is":null,"unpack_kwargs":false,"variables":[{".class":"TypeVarType","default":{".class":"AnyType","missing_import_name":null,"source_any":null,"type_of_any":4},"fullname":"trio._core._ki.KIManager._AT","id":-1,"name":"_AT","namespace":"trio._core._ki.KIManager.__lt__","upper_bound":"builtins.object","values":[],"variance":0}]}},"plugin_generated":true},"__match_args__":{".class":"SymbolTableNode","kind":"Mdef","node":{".class":"Var","flags":["is_ready","allow_incompatible_override"],"fullname":"trio._core._ki.KIManager.__match_args__","name":"__match_args__","type":{".class":"TupleType","implicit":false,"items":[{".class":"Instance","args":[],"extra_attrs":null,"last_known_value":{".class":"LiteralType","fallback":"builtins.str","value":"handler"},"type_ref":"builtins.str"}],"partial_fallback":{".class":"Instance","args":[{".class":"AnyType","missing_import_name":null,"source_any":null,"type_of_any":6}],"extra_attrs":null,"type_ref":"builtins.tuple"}}},"plugin_generated":true},"__trio__core__ki_KIManager_AttrsAttributes__":{".class":"SymbolTableNode","kind":"Mdef","node":{".class":"TypeInfo","_promote":[],"abstract_attributes":[],"alt_promote":null,"bases":[{".class":"Instance","args":[{".class":"Instance","args":[{".class":"AnyType","missing_import_name":null,"source_any":null,"type_of_any":2}],"extra_attrs":null,"type_ref":"attr.Attribute"}],"extra_attrs":null,"type_ref":"builtins.tuple"}],"dataclass_transform_spec":null,"declared_metaclass":null,"defn":{".class":"ClassDef","fullname":"trio._core._ki.KIManager.__trio__core__ki_KIManager_AttrsAttributes__","name":"__trio__core__ki_KIManager_AttrsAttributes__","type_vars":[]},"deletable_attributes":[],"deprecated":null,"flags":[],"fullname":"trio._core._ki.KIManager.__trio__core__ki_KIManager_AttrsAttributes__","has_param_spec_type":false,"metaclass_type":null,"metadata":{},"module_name":"trio._core._ki","mro":["trio._core._ki.KIManager.__trio__core__ki_KIManager_AttrsAttributes__","builtins.tuple","typing.Sequence","typing.Reversible","typing.Collection","typing.Iterable","typing.Container","builtins.object"],"names":{".class":"SymbolTable","handler":{".class":"SymbolTableNode","kind":"Mdef","node":{".class":"Var","flags":["is_property","is_ready"],"fullname":"handler","name":"handler","type":{".class":"Instance","args":[{".class":"UnionType","items":[{".class":"CallableType","arg_kinds":[0,0],"arg_names":[null,null],"arg_types":["builtins.int",{".class":"UnionType","items":["types.FrameType",{".class":"NoneType"}],"uses_pep604_syntax":true}],"bound_args":[],"def_extras":{},"fallback":"builtins.function","from_concatenate":false,"implicit":false,"imprecise_arg_kinds":false,"is_ellipsis_args":false,"name":null,"ret_type":{".class":"NoneType"},"type_guard":null,"type_is":null,"unpack_kwargs":false,"variables":[]},{".class":"NoneType"}],"uses_pep604_syntax":true}],"extra_attrs":null,"type_ref":"attr.Attribute"}},"plugin_generated":true}},"self_type":null,"slots":null,"tuple_type":null,"type_vars":[],"typeddict_type":null},"plugin_generated":true},"close":{".class":"SymbolTableNode","kind":"Mdef","node":{".class":"FuncDef","abstract_status":0,"arg_kinds":[0],"arg_names":["self"],"dataclass_transform_spec":null,"deprecated":null,"flags":[],"fullname":"trio._core._ki.KIManager.close","name":"close","type":{".class":"CallableType","arg_kinds":[0],"arg_names":["self"],"arg_types":["trio._core._ki.KIManager"],"bound_args":[],"def_extras":{"first_arg":"self"},"fallback":"builtins.function","from_concatenate":false,"implicit":false,"imprecise_arg_kinds":false,"is_ellipsis_args":false,"name":"close of KIManager","ret_type":{".class":"NoneType"},"type_guard":null,"type_is":null,"unpack_kwargs":false,"variables":[]}}},"handler":{".class":"SymbolTableNode","kind":"Mdef","node":{".class":"Var","flags":["is_ready","has_explicit_value"],"fullname":"trio._core._ki.KIManager.handler","name":"handler","type":{".class":"UnionType","items":[{".class":"CallableType","arg_kinds":[0,0],"arg_names":[null,null],"arg_types":["builtins.int",{".class":"UnionType","items":["types.FrameType",{".class":"NoneType"}],"uses_pep604_syntax":true}],"bound_args":[],"def_extras":{},"fallback":"builtins.function","from_concatenate":false,"implicit":false,"imprecise_arg_kinds":false,"is_ellipsis_args":false,"name":null,"ret_type":{".class":"NoneType"},"type_guard":null,"type_is":null,"unpack_kwargs":false,"variables":[]},{".class":"NoneType"}],"uses_pep604_syntax":true}}},"install":{".class":"SymbolTableNode","kind":"Mdef","node":{".class":"FuncDef","abstract_status":0,"arg_kinds":[0,0,0],"arg_names":["self","deliver_cb","restrict_keyboard_interrupt_to_checkpoints"],"dataclass_transform_spec":null,"deprecated":null,"flags":[],"fullname":"trio._core._ki.KIManager.install","name":"install","type":{".class":"CallableType","arg_kinds":[0,0,0],"arg_names":["self","deliver_cb","restrict_keyboard_interrupt_to_checkpoints"],"arg_types":["trio._core._ki.KIManager",{".class":"CallableType","arg_kinds":[],"arg_names":[],"arg_types":[],"bound_args":[],"def_extras":{},"fallback":"builtins.function","from_concatenate":false,"implicit":false,"imprecise_arg_kinds":false,"is_ellipsis_args":false,"name":null,"ret_type":"builtins.object","type_guard":null,"type_is":null,"unpack_kwargs":false,"variables":[]},"builtins.bool"],"bound_args":[],"def_extras":{"first_arg":"self"},"fallback":"builtins.function","from_concatenate":false,"implicit":false,"imprecise_arg_kinds":false,"is_ellipsis_args":false,"name":"install of KIManager","ret_type":{".class":"NoneType"},"type_guard":null,"type_is":null,"unpack_kwargs":false,"variables":[]}}}},"self_type":{".class":"TypeVarType","default":{".class":"AnyType","missing_import_name":null,"source_any":null,"type_of_any":4},"fullname":"trio._core._ki.KIManager.Self","id":0,"name":"Self","namespace":"","upper_bound":"trio._core._ki.KIManager","values":[],"variance":0},"slots":null,"tuple_type":null,"type_vars":[],"typeddict_type":null}},"Protocol":{".class":"SymbolTableNode","cross_ref":"typing.Protocol","kind":"Gdef"},"Self":{".class":"SymbolTableNode","cross_ref":"typing.Self","kind":"Gdef"},"TYPE_CHECKING":{".class":"SymbolTableNode","cross_ref":"typing.TYPE_CHECKING","kind":"Gdef"},"TypeGuard":{".class":"SymbolTableNode","cross_ref":"typing.TypeGuard","kind":"Gdef"},"TypeVar":{".class":"SymbolTableNode","cross_ref":"typing.TypeVar","kind":"Gdef"},"WeakKeyIdentityDictionary":{".class":"SymbolTableNode","kind":"Gdef","node":{".class":"TypeInfo","_promote":[],"abstract_attributes":[],"alt_promote":null,"bases":["builtins.object"],"dataclass_transform_spec":null,"declared_metaclass":null,"defn":{".class":"ClassDef","fullname":"trio._core._ki.WeakKeyIdentityDictionary","name":"WeakKeyIdentityDictionary","type_vars":[{".class":"TypeVarType","default":{".class":"AnyType","missing_import_name":null,"source_any":null,"type_of_any":4},"fullname":"trio._core._ki._KT","id":1,"name":"_KT","namespace":"trio._core._ki.WeakKeyIdentityDictionary","upper_bound":"builtins.object","values":[],"variance":0},{".class":"TypeVarType","default":{".class":"AnyType","missing_import_name":null,"source_any":null,"type_of_any":4},"fullname":"trio._core._ki._VT","id":2,"name":"_VT","namespace":"trio._core._ki.WeakKeyIdentityDictionary","upper_bound":"builtins.object","values":[],"variance":0}]},"deletable_attributes":[],"deprecated":null,"flags":[],"fullname":"trio._core._ki.WeakKeyIdentityDictionary","has_param_spec_type":false,"metaclass_type":null,"metadata":{},"module_name":"trio._core._ki","mro":["trio._core._ki.WeakKeyIdentityDictionary","builtins.object"],"names":{".class":"SymbolTable","__getitem__":{".class":"SymbolTableNode","kind":"Mdef","node":{".class":"FuncDef","abstract_status":0,"arg_kinds":[0,0],"arg_names":[null,null],"dataclass_transform_spec":null,"deprecated":null,"flags":[],"fullname":"trio._core._ki.WeakKeyIdentityDictionary.__getitem__","name":"__getitem__","type":{".class":"CallableType","arg_kinds":[0,0],"arg_names":[null,null],"arg_types":[{".class":"Instance","args":[{".class":"TypeVarType","default":{".class":"AnyType","missing_import_name":null,"source_any":null,"type_of_any":4},"fullname":"trio._core._ki._KT","id":1,"name":"_KT","namespace":"trio._core._ki.WeakKeyIdentityDictionary","upper_bound":"builtins.object","values":[],"variance":0},{".class":"TypeVarType","default":{".class":"AnyType","missing_import_name":null,"source_any":null,"type_of_any":4},"fullname":"trio._core._ki._VT","id":2,"name":"_VT","namespace":"trio._core._ki.WeakKeyIdentityDictionary","upper_bound":"builtins.object","values":[],"variance":0}],"extra_attrs":null,"type_ref":"trio._core._ki.WeakKeyIdentityDictionary"},{".class":"TypeVarType","default":{".class":"AnyType","missing_import_name":null,"source_any":null,"type_of_any":4},"fullname":"trio._core._ki._KT","id":1,"name":"_KT","namespace":"trio._core._ki.WeakKeyIdentityDictionary","upper_bound":"builtins.object","values":[],"variance":0}],"bound_args":[],"def_extras":{"first_arg":"self"},"fallback":"builtins.function","from_concatenate":false,"implicit":false,"imprecise_arg_kinds":false,"is_ellipsis_args":false,"name":"__getitem__ of WeakKeyIdentityDictionary","ret_type":{".class":"TypeVarType","default":{".class":"AnyType","missing_import_name":null,"source_any":null,"type_of_any":4},"fullname":"trio._core._ki._VT","id":2,"name":"_VT","namespace":"trio._core._ki.WeakKeyIdentityDictionary","upper_bound":"builtins.object","values":[],"variance":0},"type_guard":null,"type_is":null,"unpack_kwargs":false,"variables":[]}}},"__init__":{".class":"SymbolTableNode","kind":"Mdef","node":{".class":"FuncDef","abstract_status":0,"arg_kinds":[0],"arg_names":["self"],"dataclass_transform_spec":null,"deprecated":null,"flags":[],"fullname":"trio._core._ki.WeakKeyIdentityDictionary.__init__","name":"__init__","type":{".class":"CallableType","arg_kinds":[0],"arg_names":["self"],"arg_types":[{".class":"Instance","args":[{".class":"TypeVarType","default":{".class":"AnyType","missing_import_name":null,"source_any":null,"type_of_any":4},"fullname":"trio._core._ki._KT","id":1,"name":"_KT","namespace":"trio._core._ki.WeakKeyIdentityDictionary","upper_bound":"builtins.object","values":[],"variance":0},{".class":"TypeVarType","default":{".class":"AnyType","missing_import_name":null,"source_any":null,"type_of_any":4},"fullname":"trio._core._ki._VT","id":2,"name":"_VT","namespace":"trio._core._ki.WeakKeyIdentityDictionary","upper_bound":"builtins.object","values":[],"variance":0}],"extra_attrs":null,"type_ref":"trio._core._ki.WeakKeyIdentityDictionary"}],"bound_args":[],"def_extras":{"first_arg":"self"},"fallback":"builtins.function","from_concatenate":false,"implicit":false,"imprecise_arg_kinds":false,"is_ellipsis_args":false,"name":"__init__ of WeakKeyIdentityDictionary","ret_type":{".class":"NoneType"},"type_guard":null,"type_is":null,"unpack_kwargs":false,"variables":[]}}},"__setitem__":{".class":"SymbolTableNode","kind":"Mdef","node":{".class":"FuncDef","abstract_status":0,"arg_kinds":[0,0,0],"arg_names":[null,null,null],"dataclass_transform_spec":null,"deprecated":null,"flags":[],"fullname":"trio._core._ki.WeakKeyIdentityDictionary.__setitem__","name":"__setitem__","type":{".class":"CallableType","arg_kinds":[0,0,0],"arg_names":[null,null,null],"arg_types":[{".class":"Instance","args":[{".class":"TypeVarType","default":{".class":"AnyType","missing_import_name":null,"source_any":null,"type_of_any":4},"fullname":"trio._core._ki._KT","id":1,"name":"_KT","namespace":"trio._core._ki.WeakKeyIdentityDictionary","upper_bound":"builtins.object","values":[],"variance":0},{".class":"TypeVarType","default":{".class":"AnyType","missing_import_name":null,"source_any":null,"type_of_any":4},"fullname":"trio._core._ki._VT","id":2,"name":"_VT","namespace":"trio._core._ki.WeakKeyIdentityDictionary","upper_bound":"builtins.object","values":[],"variance":0}],"extra_attrs":null,"type_ref":"trio._core._ki.WeakKeyIdentityDictionary"},{".class":"TypeVarType","default":{".class":"AnyType","missing_import_name":null,"source_any":null,"type_of_any":4},"fullname":"trio._core._ki._KT","id":1,"name":"_KT","namespace":"trio._core._ki.WeakKeyIdentityDictionary","upper_bound":"builtins.object","values":[],"variance":0},{".class":"TypeVarType","default":{".class":"AnyType","missing_import_name":null,"source_any":null,"type_of_any":4},"fullname":"trio._core._ki._VT","id":2,"name":"_VT","namespace":"trio._core._ki.WeakKeyIdentityDictionary","upper_bound":"builtins.object","values":[],"variance":0}],"bound_args":[],"def_extras":{"first_arg":"self"},"fallback":"builtins.function","from_concatenate":false,"implicit":false,"imprecise_arg_kinds":false,"is_ellipsis_args":false,"name":"__setitem__ of WeakKeyIdentityDictionary","ret_type":{".class":"NoneType"},"type_guard":null,"type_is":null,"unpack_kwargs":false,"variables":[]}}},"_data":{".class":"SymbolTableNode","implicit":true,"kind":"Mdef","node":{".class":"Var","flags":["explicit_self_type","is_ready","is_inferred"],"fullname":"trio._core._ki.WeakKeyIdentityDictionary._data","name":"_data","type":{".class":"Instance","args":[{".class":"Instance","args":[{".class":"TypeVarType","default":{".class":"AnyType","missing_import_name":null,"source_any":null,"type_of_any":4},"fullname":"trio._core._ki._KT","id":1,"name":"_KT","namespace":"trio._core._ki.WeakKeyIdentityDictionary","upper_bound":"builtins.object","values":[],"variance":0}],"extra_attrs":null,"type_ref":"trio._core._ki._IdRef"},{".class":"TypeVarType","default":{".class":"AnyType","missing_import_name":null,"source_any":null,"type_of_any":4},"fullname":"trio._core._ki._VT","id":2,"name":"_VT","namespace":"trio._core._ki.WeakKeyIdentityDictionary","upper_bound":"builtins.object","values":[],"variance":0}],"extra_attrs":null,"type_ref":"builtins.dict"}}},"_remove":{".class":"SymbolTableNode","implicit":true,"kind":"Mdef","node":{".class":"Var","flags":["is_inferred"],"fullname":"trio._core._ki.WeakKeyIdentityDictionary._remove","name":"_remove","type":{".class":"CallableType","arg_kinds":[0,1],"arg_names":["k","selfref"],"arg_types":[{".class":"Instance","args":[{".class":"TypeVarType","default":{".class":"AnyType","missing_import_name":null,"source_any":null,"type_of_any":4},"fullname":"trio._core._ki._KT","id":1,"name":"_KT","namespace":"trio._core._ki.WeakKeyIdentityDictionary","upper_bound":"builtins.object","values":[],"variance":0}],"extra_attrs":null,"type_ref":"trio._core._ki._IdRef"},{".class":"Instance","args":[{".class":"Instance","args":[{".class":"TypeVarType","default":{".class":"AnyType","missing_import_name":null,"source_any":null,"type_of_any":4},"fullname":"trio._core._ki._KT","id":1,"name":"_KT","namespace":"trio._core._ki.WeakKeyIdentityDictionary","upper_bound":"builtins.object","values":[],"variance":0},{".class":"TypeVarType","default":{".class":"AnyType","missing_import_name":null,"source_any":null,"type_of_any":4},"fullname":"trio._core._ki._VT","id":2,"name":"_VT","namespace":"trio._core._ki.WeakKeyIdentityDictionary","upper_bound":"builtins.object","values":[],"variance":0}],"extra_attrs":null,"type_ref":"trio._core._ki.WeakKeyIdentityDictionary"}],"extra_attrs":null,"type_ref":"weakref.ReferenceType"}],"bound_args":[],"def_extras":{"first_arg":null},"fallback":"builtins.function","from_concatenate":false,"implicit":false,"imprecise_arg_kinds":false,"is_ellipsis_args":false,"name":null,"ret_type":{".class":"NoneType"},"type_guard":null,"type_is":null,"unpack_kwargs":false,"variables":[]}}}},"self_type":{".class":"TypeVarType","default":{".class":"AnyType","missing_import_name":null,"source_any":null,"type_of_any":4},"fullname":"trio._core._ki.WeakKeyIdentityDictionary.Self","id":0,"name":"Self","namespace":"","upper_bound":{".class":"Instance","args":[{".class":"TypeVarType","default":{".class":"AnyType","missing_import_name":null,"source_any":null,"type_of_any":4},"fullname":"trio._core._ki._KT","id":1,"name":"_KT","namespace":"trio._core._ki.WeakKeyIdentityDictionary","upper_bound":"builtins.object","values":[],"variance":0},{".class":"TypeVarType","default":{".class":"AnyType","missing_import_name":null,"source_any":null,"type_of_any":4},"fullname":"trio._core._ki._VT","id":2,"name":"_VT","namespace":"trio._core._ki.WeakKeyIdentityDictionary","upper_bound":"builtins.object","values":[],"variance":0}],"extra_attrs":null,"type_ref":"trio._core._ki.WeakKeyIdentityDictionary"},"values":[],"variance":0},"slots":null,"tuple_type":null,"type_vars":["_KT","_VT"],"typeddict_type":null}},"_CODE_KI_PROTECTION_STATUS_WMAP":{".class":"SymbolTableNode","kind":"Gdef","node":{".class":"Var","flags":["is_ready","has_explicit_value"],"fullname":"trio._core._ki._CODE_KI_PROTECTION_STATUS_WMAP","name":"_CODE_KI_PROTECTION_STATUS_WMAP","type":{".class":"Instance","args":["types.CodeType","builtins.bool"],"extra_attrs":null,"type_ref":"trio._core._ki.WeakKeyIdentityDictionary"}}},"_IdRef":{".class":"SymbolTableNode","kind":"Gdef","node":{".class":"TypeInfo","_promote":[],"abstract_attributes":[],"alt_promote":null,"bases":[{".class":"Instance","args":[{".class":"TypeVarType","default":{".class":"AnyType","missing_import_name":null,"source_any":null,"type_of_any":4},"fullname":"trio._core._ki._T","id":1,"name":"_T","namespace":"trio._core._ki._IdRef","upper_bound":"builtins.object","values":[],"variance":0}],"extra_attrs":null,"type_ref":"weakref.ReferenceType"}],"dataclass_transform_spec":null,"declared_metaclass":null,"defn":{".class":"ClassDef","fullname":"trio._core._ki._IdRef","name":"_IdRef","type_vars":[{".class":"TypeVarType","default":{".class":"AnyType","missing_import_name":null,"source_any":null,"type_of_any":4},"fullname":"trio._core._ki._T","id":1,"name":"_T","namespace":"trio._core._ki._IdRef","upper_bound":"builtins.object","values":[],"variance":0}]},"deletable_attributes":[],"deprecated":null,"flags":[],"fullname":"trio._core._ki._IdRef","has_param_spec_type":false,"metaclass_type":null,"metadata":{},"module_name":"trio._core._ki","mro":["trio._core._ki._IdRef","weakref.ReferenceType","builtins.object"],"names":{".class":"SymbolTable","__eq__":{".class":"SymbolTableNode","kind":"Mdef","node":{".class":"FuncDef","abstract_status":0,"arg_kinds":[0,0],"arg_names":[null,null],"dataclass_transform_spec":null,"deprecated":null,"flags":[],"fullname":"trio._core._ki._IdRef.__eq__","name":"__eq__","type":{".class":"CallableType","arg_kinds":[0,0],"arg_names":[null,null],"arg_types":[{".class":"Instance","args":[{".class":"TypeVarType","default":{".class":"AnyType","missing_import_name":null,"source_any":null,"type_of_any":4},"fullname":"trio._core._ki._T","id":1,"name":"_T","namespace":"trio._core._ki._IdRef","upper_bound":"builtins.object","values":[],"variance":0}],"extra_attrs":null,"type_ref":"trio._core._ki._IdRef"},"builtins.object"],"bound_args":[],"def_extras":{"first_arg":"self"},"fallback":"builtins.function","from_concatenate":false,"implicit":false,"imprecise_arg_kinds":false,"is_ellipsis_args":false,"name":"__eq__ of _IdRef","ret_type":"builtins.bool","type_guard":null,"type_is":null,"unpack_kwargs":false,"variables":[]}}},"__hash__":{".class":"SymbolTableNode","kind":"Mdef","node":{".class":"FuncDef","abstract_status":0,"arg_kinds":[0],"arg_names":["self"],"dataclass_transform_spec":null,"deprecated":null,"flags":[],"fullname":"trio._core._ki._IdRef.__hash__","name":"__hash__","type":{".class":"CallableType","arg_kinds":[0],"arg_names":["self"],"arg_types":[{".class":"Instance","args":[{".class":"TypeVarType","default":{".class":"AnyType","missing_import_name":null,"source_any":null,"type_of_any":4},"fullname":"trio._core._ki._T","id":1,"name":"_T","namespace":"trio._core._ki._IdRef","upper_bound":"builtins.object","values":[],"variance":0}],"extra_attrs":null,"type_ref":"trio._core._ki._IdRef"}],"bound_args":[],"def_extras":{"first_arg":"self"},"fallback":"builtins.function","from_concatenate":false,"implicit":false,"imprecise_arg_kinds":false,"is_ellipsis_args":false,"name":"__hash__ of _IdRef","ret_type":"builtins.int","type_guard":null,"type_is":null,"unpack_kwargs":false,"variables":[]}}},"__ne__":{".class":"SymbolTableNode","kind":"Mdef","node":{".class":"FuncDef","abstract_status":0,"arg_kinds":[0,0],"arg_names":[null,null],"dataclass_transform_spec":null,"deprecated":null,"flags":[],"fullname":"trio._core._ki._IdRef.__ne__","name":"__ne__","type":{".class":"CallableType","arg_kinds":[0,0],"arg_names":[null,null],"arg_types":[{".class":"Instance","args":[{".class":"TypeVarType","default":{".class":"AnyType","missing_import_name":null,"source_any":null,"type_of_any":4},"fullname":"trio._core._ki._T","id":1,"name":"_T","namespace":"trio._core._ki._IdRef","upper_bound":"builtins.object","values":[],"variance":0}],"extra_attrs":null,"type_ref":"trio._core._ki._IdRef"},"builtins.object"],"bound_args":[],"def_extras":{"first_arg":"self"},"fallback":"builtins.function","from_concatenate":false,"implicit":false,"imprecise_arg_kinds":false,"is_ellipsis_args":false,"name":"__ne__ of _IdRef","ret_type":"builtins.bool","type_guard":null,"type_is":null,"unpack_kwargs":false,"variables":[]}}},"__new__":{".class":"SymbolTableNode","kind":"Mdef","node":{".class":"FuncDef","abstract_status":0,"arg_kinds":[0,0,1],"arg_names":[null,null,null],"dataclass_transform_spec":null,"deprecated":null,"flags":["is_static"],"fullname":"trio._core._ki._IdRef.__new__","name":"__new__","type":{".class":"CallableType","arg_kinds":[0,0,1],"arg_names":[null,null,null],"arg_types":[{".class":"TypeType","item":{".class":"TypeVarType","default":{".class":"AnyType","missing_import_name":null,"source_any":null,"type_of_any":4},"fullname":"trio._core._ki._IdRef.Self","id":0,"name":"Self","namespace":"","upper_bound":{".class":"Instance","args":[{".class":"TypeVarType","default":{".class":"AnyType","missing_import_name":null,"source_any":null,"type_of_any":4},"fullname":"trio._core._ki._T","id":1,"name":"_T","namespace":"trio._core._ki._IdRef","upper_bound":"builtins.object","values":[],"variance":0}],"extra_attrs":null,"type_ref":"trio._core._ki._IdRef"},"values":[],"variance":0}},{".class":"TypeVarType","default":{".class":"AnyType","missing_import_name":null,"source_any":null,"type_of_any":4},"fullname":"trio._core._ki._T","id":1,"name":"_T","namespace":"trio._core._ki._IdRef","upper_bound":"builtins.object","values":[],"variance":0},{".class":"UnionType","items":[{".class":"CallableType","arg_kinds":[0],"arg_names":[null],"arg_types":[{".class":"TypeVarType","default":{".class":"AnyType","missing_import_name":null,"source_any":null,"type_of_any":4},"fullname":"trio._core._ki._IdRef.Self","id":0,"name":"Self","namespace":"","upper_bound":{".class":"Instance","args":[{".class":"TypeVarType","default":{".class":"AnyType","missing_import_name":null,"source_any":null,"type_of_any":4},"fullname":"trio._core._ki._T","id":1,"name":"_T","namespace":"trio._core._ki._IdRef","upper_bound":"builtins.object","values":[],"variance":0}],"extra_attrs":null,"type_ref":"trio._core._ki._IdRef"},"values":[],"variance":0}],"bound_args":[],"def_extras":{},"fallback":"builtins.function","from_concatenate":false,"implicit":false,"imprecise_arg_kinds":false,"is_ellipsis_args":false,"name":null,"ret_type":"builtins.object","type_guard":null,"type_is":null,"unpack_kwargs":false,"variables":[]},{".class":"NoneType"}],"uses_pep604_syntax":true}],"bound_args":[],"def_extras":{"first_arg":null},"fallback":"builtins.function","from_concatenate":false,"implicit":false,"imprecise_arg_kinds":false,"is_ellipsis_args":false,"name":"__new__ of _IdRef","ret_type":{".class":"TypeVarType","default":{".class":"AnyType","missing_import_name":null,"source_any":null,"type_of_any":4},"fullname":"trio._core._ki._IdRef.Self","id":0,"name":"Self","namespace":"","upper_bound":{".class":"Instance","args":[{".class":"TypeVarType","default":{".class":"AnyType","missing_import_name":null,"source_any":null,"type_of_any":4},"fullname":"trio._core._ki._T","id":1,"name":"_T","namespace":"trio._core._ki._IdRef","upper_bound":"builtins.object","values":[],"variance":0}],"extra_attrs":null,"type_ref":"trio._core._ki._IdRef"},"values":[],"variance":0},"type_guard":null,"type_is":null,"unpack_kwargs":false,"variables":[{".class":"TypeVarType","default":{".class":"AnyType","missing_import_name":null,"source_any":null,"type_of_any":4},"fullname":"trio._core._ki._IdRef.Self","id":0,"name":"Self","namespace":"","upper_bound":{".class":"Instance","args":[{".class":"TypeVarType","default":{".class":"AnyType","missing_import_name":null,"source_any":null,"type_of_any":4},"fullname":"trio._core._ki._T","id":1,"name":"_T","namespace":"trio._core._ki._IdRef","upper_bound":"builtins.object","values":[],"variance":0}],"extra_attrs":null,"type_ref":"trio._core._ki._IdRef"},"values":[],"variance":0}]}}},"__slots__":{".class":"SymbolTableNode","kind":"Mdef","node":{".class":"Var","flags":["is_initialized_in_class","is_inferred","has_explicit_value","allow_incompatible_override"],"fullname":"trio._core._ki._IdRef.__slots__","name":"__slots__","type":{".class":"TupleType","implicit":false,"items":["builtins.str"],"partial_fallback":{".class":"Instance","args":[{".class":"AnyType","missing_import_name":null,"source_any":null,"type_of_any":6}],"extra_attrs":null,"type_ref":"builtins.tuple"}}}},"_hash":{".class":"SymbolTableNode","kind":"Mdef","node":{".class":"Var","flags":["is_initialized_in_class","is_ready"],"fullname":"trio._core._ki._IdRef._hash","name":"_hash","type":"builtins.int"}}},"self_type":{".class":"TypeVarType","default":{".class":"AnyType","missing_import_name":null,"source_any":null,"type_of_any":4},"fullname":"trio._core._ki._IdRef.Self","id":0,"name":"Self","namespace":"","upper_bound":{".class":"Instance","args":[{".class":"TypeVarType","default":{".class":"AnyType","missing_import_name":null,"source_any":null,"type_of_any":4},"fullname":"trio._core._ki._T","id":1,"name":"_T","namespace":"trio._core._ki._IdRef","upper_bound":"builtins.object","values":[],"variance":0}],"extra_attrs":null,"type_ref":"trio._core._ki._IdRef"},"values":[],"variance":0},"slots":null,"tuple_type":null,"type_vars":["_T"],"typeddict_type":null}},"_KT":{".class":"SymbolTableNode","kind":"Gdef","node":{".class":"TypeVarExpr","default":{".class":"AnyType","missing_import_name":null,"source_any":null,"type_of_any":4},"fullname":"trio._core._ki._KT","name":"_KT","upper_bound":"builtins.object","values":[],"variance":0}},"_SupportsCode":{".class":"SymbolTableNode","kind":"Gdef","node":{".class":"TypeInfo","_promote":[],"abstract_attributes":[["__code__",1]],"alt_promote":null,"bases":["builtins.object"],"dataclass_transform_spec":null,"declared_metaclass":null,"defn":{".class":"ClassDef","fullname":"trio._core._ki._SupportsCode","name":"_SupportsCode","type_vars":[]},"deletable_attributes":[],"deprecated":null,"flags":["is_abstract","is_protocol"],"fullname":"trio._core._ki._SupportsCode","has_param_spec_type":false,"metaclass_type":"abc.ABCMeta","metadata":{},"module_name":"trio._core._ki","mro":["trio._core._ki._SupportsCode","builtins.object"],"names":{".class":"SymbolTable","__code__":{".class":"SymbolTableNode","kind":"Mdef","node":{".class":"Var","flags":["is_initialized_in_class","is_abstract_var","is_ready"],"fullname":"trio._core._ki._SupportsCode.__code__","name":"__code__","type":"types.CodeType"}}},"self_type":{".class":"TypeVarType","default":{".class":"AnyType","missing_import_name":null,"source_any":null,"type_of_any":4},"fullname":"trio._core._ki._SupportsCode.Self","id":0,"name":"Self","namespace":"","upper_bound":"trio._core._ki._SupportsCode","values":[],"variance":0},"slots":null,"tuple_type":null,"type_vars":[],"typeddict_type":null}},"_T":{".class":"SymbolTableNode","kind":"Gdef","node":{".class":"TypeVarExpr","default":{".class":"AnyType","missing_import_name":null,"source_any":null,"type_of_any":4},"fullname":"trio._core._ki._T","name":"_T","upper_bound":"builtins.object","values":[],"variance":0}},"_T_supports_code":{".class":"SymbolTableNode","kind":"Gdef","node":{".class":"TypeVarExpr","default":{".class":"AnyType","missing_import_name":null,"source_any":null,"type_of_any":4},"fullname":"trio._core._ki._T_supports_code","name":"_T_supports_code","upper_bound":"trio._core._ki._SupportsCode","values":[],"variance":0}},"_VT":{".class":"SymbolTableNode","kind":"Gdef","node":{".class":"TypeVarExpr","default":{".class":"AnyType","missing_import_name":null,"source_any":null,"type_of_any":4},"fullname":"trio._core._ki._VT","name":"_VT","upper_bound":"builtins.object","values":[],"variance":0}},"__annotations__":{".class":"SymbolTableNode","kind":"Gdef","node":{".class":"Var","flags":["is_ready"],"fullname":"trio._core._ki.__annotations__","name":"__annotations__","type":{".class":"Instance","args":["builtins.str",{".class":"AnyType","missing_import_name":null,"source_any":null,"type_of_any":6}],"extra_attrs":null,"type_ref":"builtins.dict"}}},"__doc__":{".class":"SymbolTableNode","kind":"Gdef","node":{".class":"Var","flags":["is_ready"],"fullname":"trio._core._ki.__doc__","name":"__doc__","type":"builtins.str"}},"__file__":{".class":"SymbolTableNode","kind":"Gdef","node":{".class":"Var","flags":["is_ready"],"fullname":"trio._core._ki.__file__","name":"__file__","type":"builtins.str"}},"__name__":{".class":"SymbolTableNode","kind":"Gdef","node":{".class":"Var","flags":["is_ready"],"fullname":"trio._core._ki.__name__","name":"__name__","type":"builtins.str"}},"__package__":{".class":"SymbolTableNode","kind":"Gdef","node":{".class":"Var","flags":["is_ready"],"fullname":"trio._core._ki.__package__","name":"__package__","type":"builtins.str"}},"__spec__":{".class":"SymbolTableNode","kind":"Gdef","node":{".class":"Var","flags":["is_ready"],"fullname":"trio._core._ki.__spec__","name":"__spec__","type":"_frozen_importlib.ModuleSpec"}},"annotations":{".class":"SymbolTableNode","cross_ref":"__future__.annotations","kind":"Gdef"},"attrs":{".class":"SymbolTableNode","cross_ref":"attrs","kind":"Gdef"},"currently_ki_protected":{".class":"SymbolTableNode","kind":"Gdef","node":{".class":"FuncDef","abstract_status":0,"arg_kinds":[],"arg_names":[],"dataclass_transform_spec":null,"deprecated":null,"flags":[],"fullname":"trio._core._ki.currently_ki_protected","name":"currently_ki_protected","type":{".class":"CallableType","arg_kinds":[],"arg_names":[],"arg_types":[],"bound_args":[],"def_extras":{"first_arg":null},"fallback":"builtins.function","from_concatenate":false,"implicit":false,"imprecise_arg_kinds":false,"is_ellipsis_args":false,"name":"currently_ki_protected","ret_type":"builtins.bool","type_guard":null,"type_is":null,"unpack_kwargs":false,"variables":[]}}},"disable_ki_protection":{".class":"SymbolTableNode","kind":"Gdef","node":{".class":"FuncDef","abstract_status":0,"arg_kinds":[0],"arg_names":[null],"dataclass_transform_spec":null,"deprecated":null,"flags":[],"fullname":"trio._core._ki.disable_ki_protection","name":"disable_ki_protection","type":{".class":"CallableType","arg_kinds":[0],"arg_names":[null],"arg_types":[{".class":"TypeVarType","default":{".class":"AnyType","missing_import_name":null,"source_any":null,"type_of_any":4},"fullname":"trio._core._ki._T_supports_code","id":-1,"name":"_T_supports_code","namespace":"trio._core._ki.disable_ki_protection","upper_bound":"trio._core._ki._SupportsCode","values":[],"variance":0}],"bound_args":[],"def_extras":{"first_arg":null},"fallback":"builtins.function","from_concatenate":false,"implicit":false,"imprecise_arg_kinds":false,"is_ellipsis_args":false,"name":"disable_ki_protection","ret_type":{".class":"TypeVarType","default":{".class":"AnyType","missing_import_name":null,"source_any":null,"type_of_any":4},"fullname":"trio._core._ki._T_supports_code","id":-1,"name":"_T_supports_code","namespace":"trio._core._ki.disable_ki_protection","upper_bound":"trio._core._ki._SupportsCode","values":[],"variance":0},"type_guard":null,"type_is":null,"unpack_kwargs":false,"variables":[{".class":"TypeVarType","default":{".class":"AnyType","missing_import_name":null,"source_any":null,"type_of_any":4},"fullname":"trio._core._ki._T_supports_code","id":-1,"name":"_T_supports_code","namespace":"trio._core._ki.disable_ki_protection","upper_bound":"trio._core._ki._SupportsCode","values":[],"variance":0}]}}},"enable_ki_protection":{".class":"SymbolTableNode","kind":"Gdef","node":{".class":"FuncDef","abstract_status":0,"arg_kinds":[0],"arg_names":[null],"dataclass_transform_spec":null,"deprecated":null,"flags":[],"fullname":"trio._core._ki.enable_ki_protection","name":"enable_ki_protection","type":{".class":"CallableType","arg_kinds":[0],"arg_names":[null],"arg_types":[{".class":"TypeVarType","default":{".class":"AnyType","missing_import_name":null,"source_any":null,"type_of_any":4},"fullname":"trio._core._ki._T_supports_code","id":-1,"name":"_T_supports_code","namespace":"trio._core._ki.enable_ki_protection","upper_bound":"trio._core._ki._SupportsCode","values":[],"variance":0}],"bound_args":[],"def_extras":{"first_arg":null},"fallback":"builtins.function","from_concatenate":false,"implicit":false,"imprecise_arg_kinds":false,"is_ellipsis_args":false,"name":"enable_ki_protection","ret_type":{".class":"TypeVarType","default":{".class":"AnyType","missing_import_name":null,"source_any":null,"type_of_any":4},"fullname":"trio._core._ki._T_supports_code","id":-1,"name":"_T_supports_code","namespace":"trio._core._ki.enable_ki_protection","upper_bound":"trio._core._ki._SupportsCode","values":[],"variance":0},"type_guard":null,"type_is":null,"unpack_kwargs":false,"variables":[{".class":"TypeVarType","default":{".class":"AnyType","missing_import_name":null,"source_any":null,"type_of_any":4},"fullname":"trio._core._ki._T_supports_code","id":-1,"name":"_T_supports_code","namespace":"trio._core._ki.enable_ki_protection","upper_bound":"trio._core._ki._SupportsCode","values":[],"variance":0}]}}},"is_main_thread":{".class":"SymbolTableNode","cross_ref":"trio._util.is_main_thread","kind":"Gdef"},"ki_protection_enabled":{".class":"SymbolTableNode","kind":"Gdef","node":{".class":"FuncDef","abstract_status":0,"arg_kinds":[0],"arg_names":["frame"],"dataclass_transform_spec":null,"deprecated":null,"flags":[],"fullname":"trio._core._ki.ki_protection_enabled","name":"ki_protection_enabled","type":{".class":"CallableType","arg_kinds":[0],"arg_names":["frame"],"arg_types":[{".class":"UnionType","items":["types.FrameType",{".class":"NoneType"}],"uses_pep604_syntax":true}],"bound_args":[],"def_extras":{"first_arg":null},"fallback":"builtins.function","from_concatenate":false,"implicit":false,"imprecise_arg_kinds":false,"is_ellipsis_args":false,"name":"ki_protection_enabled","ret_type":"builtins.bool","type_guard":null,"type_is":null,"unpack_kwargs":false,"variables":[]}}},"legacy_isasyncgenfunction":{".class":"SymbolTableNode","kind":"Gdef","node":{".class":"FuncDef","abstract_status":0,"arg_kinds":[0],"arg_names":["obj"],"dataclass_transform_spec":null,"deprecated":null,"flags":[],"fullname":"trio._core._ki.legacy_isasyncgenfunction","name":"legacy_isasyncgenfunction","type":{".class":"CallableType","arg_kinds":[0],"arg_names":["obj"],"arg_types":["builtins.object"],"bound_args":[],"def_extras":{"first_arg":null},"fallback":"builtins.function","from_concatenate":false,"implicit":false,"imprecise_arg_kinds":false,"is_ellipsis_args":false,"name":"legacy_isasyncgenfunction","ret_type":"builtins.bool","type_guard":{".class":"CallableType","arg_kinds":[2,4],"arg_names":[null,null],"arg_types":[{".class":"AnyType","missing_import_name":null,"source_any":null,"type_of_any":2},{".class":"AnyType","missing_import_name":null,"source_any":null,"type_of_any":2}],"bound_args":[],"def_extras":{},"fallback":"builtins.function","from_concatenate":false,"implicit":false,"imprecise_arg_kinds":false,"is_ellipsis_args":true,"name":null,"ret_type":{".class":"Instance","args":["builtins.object","builtins.object"],"extra_attrs":null,"type_ref":"types.AsyncGeneratorType"},"type_guard":null,"type_is":null,"unpack_kwargs":false,"variables":[]},"type_is":null,"unpack_kwargs":false,"variables":[]}}},"signal":{".class":"SymbolTableNode","cross_ref":"signal","kind":"Gdef"},"sys":{".class":"SymbolTableNode","cross_ref":"sys","kind":"Gdef"},"types":{".class":"SymbolTableNode","cross_ref":"types","kind":"Gdef"},"weakref":{".class":"SymbolTableNode","cross_ref":"weakref","kind":"Gdef"}},"path":"/Library/Frameworks/Python.framework/Versions/3.13/lib/python3.13/site-packages/trio/_core/_ki.py"}