{".class":"MypyFile","_fullname":"app.main","future_import_flags":[],"is_partial_stub_package":false,"is_stub":false,"names":{".class":"SymbolTable","Base":{".class":"SymbolTableNode","cross_ref":"app.database.Base","kind":"Gdef"},"CORSMiddleware":{".class":"SymbolTableNode","cross_ref":"starlette.middleware.cors.CORSMiddleware","kind":"Gdef"},"FastAPI":{".class":"SymbolTableNode","cross_ref":"fastapi.applications.FastAPI","kind":"Gdef"},"Path":{".class":"SymbolTableNode","cross_ref":"pathlib.Path","kind":"Gdef"},"RedirectResponse":{".class":"SymbolTableNode","cross_ref":"starlette.responses.RedirectResponse","kind":"Gdef"},"SPAStaticFiles":{".class":"SymbolTableNode","kind":"Gdef","node":{".class":"TypeInfo","_promote":[],"abstract_attributes":[],"alt_promote":null,"bases":["starlette.staticfiles.StaticFiles"],"dataclass_transform_spec":null,"declared_metaclass":null,"defn":{".class":"ClassDef","fullname":"app.main.SPAStaticFiles","name":"SPAStaticFiles","type_vars":[]},"deletable_attributes":[],"deprecated":null,"flags":[],"fullname":"app.main.SPAStaticFiles","has_param_spec_type":false,"metaclass_type":null,"metadata":{},"module_name":"app.main","mro":["app.main.SPAStaticFiles","starlette.staticfiles.StaticFiles","builtins.object"],"names":{".class":"SymbolTable","get_response":{".class":"SymbolTableNode","kind":"Mdef","node":{".class":"FuncDef","abstract_status":0,"arg_kinds":[0,0,0],"arg_names":["self","path","scope"],"dataclass_transform_spec":null,"deprecated":null,"flags":["is_coroutine"],"fullname":"app.main.SPAStaticFiles.get_response","name":"get_response","type":{".class":"CallableType","arg_kinds":[0,0,0],"arg_names":["self","path","scope"],"arg_types":["app.main.SPAStaticFiles","builtins.str",{".class":"AnyType","missing_import_name":null,"source_any":null,"type_of_any":1}],"bound_args":[],"def_extras":{"first_arg":"self"},"fallback":"builtins.function","from_concatenate":false,"implicit":false,"imprecise_arg_kinds":false,"is_ellipsis_args":false,"name":"get_response of SPAStaticFiles","ret_type":{".class":"Instance","args":[{".class":"AnyType","missing_import_name":null,"source_any":null,"type_of_any":6},{".class":"AnyType","missing_import_name":null,"source_any":null,"type_of_any":6},{".class":"AnyType","missing_import_name":null,"source_any":null,"type_of_any":1}],"extra_attrs":null,"type_ref":"typing.Coroutine"},"type_guard":null,"type_is":null,"unpack_kwargs":false,"variables":[]}}}},"self_type":{".class":"TypeVarType","default":{".class":"AnyType","missing_import_name":null,"source_any":null,"type_of_any":4},"fullname":"app.main.SPAStaticFiles.Self","id":0,"name":"Self","namespace":"","upper_bound":"app.main.SPAStaticFiles","values":[],"variance":0},"slots":null,"tuple_type":null,"type_vars":[],"typeddict_type":null}},"StaticFiles":{".class":"SymbolTableNode","cross_ref":"starlette.staticfiles.StaticFiles","kind":"Gdef"},"__annotations__":{".class":"SymbolTableNode","kind":"Gdef","node":{".class":"Var","flags":["is_ready"],"fullname":"app.main.__annotations__","name":"__annotations__","type":{".class":"Instance","args":["builtins.str",{".class":"AnyType","missing_import_name":null,"source_any":null,"type_of_any":6}],"extra_attrs":null,"type_ref":"builtins.dict"}}},"__doc__":{".class":"SymbolTableNode","kind":"Gdef","node":{".class":"Var","flags":["is_ready"],"fullname":"app.main.__doc__","name":"__doc__","type":"builtins.str"}},"__file__":{".class":"SymbolTableNode","kind":"Gdef","node":{".class":"Var","flags":["is_ready"],"fullname":"app.main.__file__","name":"__file__","type":"builtins.str"}},"__name__":{".class":"SymbolTableNode","kind":"Gdef","node":{".class":"Var","flags":["is_ready"],"fullname":"app.main.__name__","name":"__name__","type":"builtins.str"}},"__package__":{".class":"SymbolTableNode","kind":"Gdef","node":{".class":"Var","flags":["is_ready"],"fullname":"app.main.__package__","name":"__package__","type":"builtins.str"}},"__spec__":{".class":"SymbolTableNode","kind":"Gdef","node":{".class":"Var","flags":["is_ready"],"fullname":"app.main.__spec__","name":"__spec__","type":"_frozen_importlib.ModuleSpec"}},"admin":{".class":"SymbolTableNode","cross_ref":"app.routes.admin","kind":"Gdef"},"admin_dist_dir":{".class":"SymbolTableNode","kind":"Gdef","node":{".class":"Var","flags":["is_inferred","has_explicit_value"],"fullname":"app.main.admin_dist_dir","name":"admin_dist_dir","type":"pathlib.Path"}},"admin_redirect":{".class":"SymbolTableNode","kind":"Gdef","node":{".class":"Decorator","func":{".class":"FuncDef","abstract_status":0,"arg_kinds":[],"arg_names":[],"dataclass_transform_spec":null,"deprecated":null,"flags":["is_decorated"],"fullname":"app.main.admin_redirect","name":"admin_redirect","type":null},"is_overload":false,"var":{".class":"Var","flags":["is_ready","is_inferred"],"fullname":"app.main.admin_redirect","name":"admin_redirect","type":{".class":"CallableType","arg_kinds":[],"arg_names":[],"arg_types":[],"bound_args":[],"def_extras":{"first_arg":null},"fallback":"builtins.function","from_concatenate":false,"implicit":true,"imprecise_arg_kinds":false,"is_ellipsis_args":false,"name":"admin_redirect","ret_type":{".class":"AnyType","missing_import_name":null,"source_any":null,"type_of_any":1},"type_guard":null,"type_is":null,"unpack_kwargs":false,"variables":[]}}}},"app":{".class":"SymbolTableNode","kind":"Gdef","node":{".class":"Var","flags":["is_inferred","has_explicit_value"],"fullname":"app.main.app","name":"app","type":"fastapi.applications.FastAPI"}},"auth":{".class":"SymbolTableNode","cross_ref":"app.routes.auth","kind":"Gdef"},"e":{".class":"SymbolTableNode","kind":"Gdef","node":{".class":"Var","flags":["is_inferred"],"fullname":"app.main.e","name":"e","type":{".class":"DeletedType","source":"e"}}},"engine":{".class":"SymbolTableNode","cross_ref":"app.database.engine","kind":"Gdef"},"get_system_status":{".class":"SymbolTableNode","cross_ref":"app.core.system_status.get_system_status","kind":"Gdef"},"health_check":{".class":"SymbolTableNode","kind":"Gdef","node":{".class":"Decorator","func":{".class":"FuncDef","abstract_status":0,"arg_kinds":[],"arg_names":[],"dataclass_transform_spec":null,"deprecated":null,"flags":["is_decorated"],"fullname":"app.main.health_check","name":"health_check","type":null},"is_overload":false,"var":{".class":"Var","flags":["is_ready","is_inferred"],"fullname":"app.main.health_check","name":"health_check","type":{".class":"CallableType","arg_kinds":[],"arg_names":[],"arg_types":[],"bound_args":[],"def_extras":{"first_arg":null},"fallback":"builtins.function","from_concatenate":false,"implicit":true,"imprecise_arg_kinds":false,"is_ellipsis_args":false,"name":"health_check","ret_type":{".class":"AnyType","missing_import_name":null,"source_any":null,"type_of_any":1},"type_guard":null,"type_is":null,"unpack_kwargs":false,"variables":[]}}}},"invitation":{".class":"SymbolTableNode","cross_ref":"app.routes.invitation","kind":"Gdef"},"os":{".class":"SymbolTableNode","cross_ref":"os","kind":"Gdef"},"registration":{".class":"SymbolTableNode","cross_ref":"app.routes.registration","kind":"Gdef"},"root":{".class":"SymbolTableNode","kind":"Gdef","node":{".class":"Decorator","func":{".class":"FuncDef","abstract_status":0,"arg_kinds":[],"arg_names":[],"dataclass_transform_spec":null,"deprecated":null,"flags":["is_decorated"],"fullname":"app.main.root","name":"root","type":null},"is_overload":false,"var":{".class":"Var","flags":["is_ready","is_inferred"],"fullname":"app.main.root","name":"root","type":{".class":"CallableType","arg_kinds":[],"arg_names":[],"arg_types":[],"bound_args":[],"def_extras":{"first_arg":null},"fallback":"builtins.function","from_concatenate":false,"implicit":true,"imprecise_arg_kinds":false,"is_ellipsis_args":false,"name":"root","ret_type":{".class":"AnyType","missing_import_name":null,"source_any":null,"type_of_any":1},"type_guard":null,"type_is":null,"unpack_kwargs":false,"variables":[]}}}},"services":{".class":"SymbolTableNode","cross_ref":"app.routes.services","kind":"Gdef"},"settings":{".class":"SymbolTableNode","cross_ref":"app.config.settings","kind":"Gdef"},"shutdown_event":{".class":"SymbolTableNode","kind":"Gdef","node":{".class":"Decorator","func":{".class":"FuncDef","abstract_status":0,"arg_kinds":[],"arg_names":[],"dataclass_transform_spec":null,"deprecated":null,"flags":["is_coroutine","is_decorated"],"fullname":"app.main.shutdown_event","name":"shutdown_event","type":null},"is_overload":false,"var":{".class":"Var","flags":["is_ready","is_inferred"],"fullname":"app.main.shutdown_event","name":"shutdown_event","type":{".class":"CallableType","arg_kinds":[],"arg_names":[],"arg_types":[],"bound_args":[],"def_extras":{"first_arg":null},"fallback":"builtins.function","from_concatenate":false,"implicit":true,"imprecise_arg_kinds":false,"is_ellipsis_args":false,"name":"shutdown_event","ret_type":{".class":"AnyType","missing_import_name":null,"source_any":null,"type_of_any":1},"type_guard":null,"type_is":null,"unpack_kwargs":false,"variables":[]}}}},"startup_event":{".class":"SymbolTableNode","kind":"Gdef","node":{".class":"Decorator","func":{".class":"FuncDef","abstract_status":0,"arg_kinds":[],"arg_names":[],"dataclass_transform_spec":null,"deprecated":null,"flags":["is_coroutine","is_decorated"],"fullname":"app.main.startup_event","name":"startup_event","type":null},"is_overload":false,"var":{".class":"Var","flags":["is_ready","is_inferred"],"fullname":"app.main.startup_event","name":"startup_event","type":{".class":"CallableType","arg_kinds":[],"arg_names":[],"arg_types":[],"bound_args":[],"def_extras":{"first_arg":null},"fallback":"builtins.function","from_concatenate":false,"implicit":true,"imprecise_arg_kinds":false,"is_ellipsis_args":false,"name":"startup_event","ret_type":{".class":"AnyType","missing_import_name":null,"source_any":null,"type_of_any":1},"type_guard":null,"type_is":null,"unpack_kwargs":false,"variables":[]}}}},"system":{".class":"SymbolTableNode","cross_ref":"app.routes.system","kind":"Gdef"},"upload":{".class":"SymbolTableNode","cross_ref":"app.routes.upload","kind":"Gdef"},"uvicorn":{".class":"SymbolTableNode","cross_ref":"uvicorn","kind":"Gdef"},"waitlist":{".class":"SymbolTableNode","cross_ref":"app.routes.waitlist","kind":"Gdef"},"waitlist_model":{".class":"SymbolTableNode","cross_ref":"app.models.waitlist","kind":"Gdef"}},"path":"/Volumes/Project Disk/PROJECTS/BUILDING CODEBASE/MIS_SYSTEM/MIS_SYSTEM-ENGINE_[SE]/central-auth-api/app/main.py"}